[{"place_id": 306392713, "licence": "Data \u00a9 OpenStreetMap contributors, ODbL 1.0. http://osm.org/copyright", "osm_type": "node", "osm_id": 10282194562, "lat": "33.6124787", "lon": "-117.8708029", "class": "amenity", "type": "hospital", "place_rank": 30, "importance": 9.99999999995449e-06, "addresstype": "amenity", "name": "Newport Children's Medical Group", "display_name": "Newport Children's Medical Group, 1401, Avocado Avenue, Fashion Island, Newport Center, Newport Beach, Orange County, California, 92660, United States", "boundingbox": ["33.6124287", "33.6125287", "-117.8708529", "-117.8707529"]}]